phovea_security_store_ldap/__init__.py
phovea_security_store_ldap/config.json
phovea_security_store_ldap/ldap.py
phovea_security_store_ldap/main.py
phovea_security_store_ldap-8.0.0.dist-info/LICENSE
phovea_security_store_ldap-8.0.0.dist-info/METADATA
phovea_security_store_ldap-8.0.0.dist-info/WHEEL
phovea_security_store_ldap-8.0.0.dist-info/entry_points.txt
phovea_security_store_ldap-8.0.0.dist-info/top_level.txt
phovea_security_store_ldap-8.0.0.dist-info/RECORD
