Metadata-Version: 2.1
Name: phovea-security-store-ldap
Version: 8.0.0
Summary: DEPRECATED: Security store implementation based LDAP
Home-page: https://phovea.caleydo.org
Author: The Caleydo Team
Author-email: contact@caleydo.org
License: BSD-3-Clause
Platform: UNKNOWN
Classifier: Intended Audience :: Developers
Classifier: Operating System :: OS Independent
Classifier: License :: OSI Approved :: BSD License
Classifier: Programming Language :: Python
Classifier: Programming Language :: Python :: 3.7
License-File: LICENSE
Requires-Dist: ldap3 (==2.8.1)
Requires-Dist: pyasn1 (==0.4.8)
Requires-Dist: phovea-server (<8.0.0,>=7.2.0)
